axdumper/__init__.py
axdumper/dumpers.py
axdumper/types.py
axdumper-0.1.1.dist-info/METADATA
axdumper-0.1.1.dist-info/WHEEL
axdumper-0.1.1.dist-info/RECORD
