Metadata-Version: 2.1
Name: axdumper
Version: 0.1.1
Summary: 
Author: axdjuraev
Author-email: axdjuraev@gmail.com
Requires-Python: >=3.10,<4.0
Classifier: Programming Language :: Python :: 3
Classifier: Programming Language :: Python :: 3.10
Classifier: Programming Language :: Python :: 3.11
